.class public Lcom/s1243808733/android/dx/cf/code/ByteOps;
.super Ljava/lang/Object;
.source "ByteOps.java"


# static fields
.field public static final AALOAD:I = 0x32

.field public static final AASTORE:I = 0x53

.field public static final ACONST_NULL:I = 0x1

.field public static final ALOAD:I = 0x19

.field public static final ALOAD_0:I = 0x2a

.field public static final ALOAD_1:I = 0x2b

.field public static final ALOAD_2:I = 0x2c

.field public static final ALOAD_3:I = 0x2d

.field public static final ANEWARRAY:I = 0xbd

.field public static final ARETURN:I = 0xb0

.field public static final ARRAYLENGTH:I = 0xbe

.field public static final ASTORE:I = 0x3a

.field public static final ASTORE_0:I = 0x4b

.field public static final ASTORE_1:I = 0x4c

.field public static final ASTORE_2:I = 0x4d

.field public static final ASTORE_3:I = 0x4e

.field public static final ATHROW:I = 0xbf

.field public static final BALOAD:I = 0x33

.field public static final BASTORE:I = 0x54

.field public static final BIPUSH:I = 0x10

.field public static final CALOAD:I = 0x34

.field public static final CASTORE:I = 0x55

.field public static final CHECKCAST:I = 0xc0

.field public static final CPOK_Class:I = 0x200

.field public static final CPOK_Double:I = 0x100

.field public static final CPOK_Fieldref:I = 0x800

.field public static final CPOK_Float:I = 0x40

.field public static final CPOK_Integer:I = 0x20

.field public static final CPOK_InterfaceMethodref:I = 0x2000

.field public static final CPOK_Long:I = 0x80

.field public static final CPOK_Methodref:I = 0x1000

.field public static final CPOK_String:I = 0x400

.field public static final D2F:I = 0x90

.field public static final D2I:I = 0x8e

.field public static final D2L:I = 0x8f

.field public static final DADD:I = 0x63

.field public static final DALOAD:I = 0x31

.field public static final DASTORE:I = 0x52

.field public static final DCMPG:I = 0x98

.field public static final DCMPL:I = 0x97

.field public static final DCONST_0:I = 0xe

.field public static final DCONST_1:I = 0xf

.field public static final DDIV:I = 0x6f

.field public static final DLOAD:I = 0x18

.field public static final DLOAD_0:I = 0x26

.field public static final DLOAD_1:I = 0x27

.field public static final DLOAD_2:I = 0x28

.field public static final DLOAD_3:I = 0x29

.field public static final DMUL:I = 0x6b

.field public static final DNEG:I = 0x77

.field public static final DREM:I = 0x73

.field public static final DRETURN:I = 0xaf

.field public static final DSTORE:I = 0x39

.field public static final DSTORE_0:I = 0x47

.field public static final DSTORE_1:I = 0x48

.field public static final DSTORE_2:I = 0x49

.field public static final DSTORE_3:I = 0x4a

.field public static final DSUB:I = 0x67

.field public static final DUP:I = 0x59

.field public static final DUP2:I = 0x5c

.field public static final DUP2_X1:I = 0x5d

.field public static final DUP2_X2:I = 0x5e

.field public static final DUP_X1:I = 0x5a

.field public static final DUP_X2:I = 0x5b

.field public static final F2D:I = 0x8d

.field public static final F2I:I = 0x8b

.field public static final F2L:I = 0x8c

.field public static final FADD:I = 0x62

.field public static final FALOAD:I = 0x30

.field public static final FASTORE:I = 0x51

.field public static final FCMPG:I = 0x96

.field public static final FCMPL:I = 0x95

.field public static final FCONST_0:I = 0xb

.field public static final FCONST_1:I = 0xc

.field public static final FCONST_2:I = 0xd

.field public static final FDIV:I = 0x6e

.field public static final FLOAD:I = 0x17

.field public static final FLOAD_0:I = 0x22

.field public static final FLOAD_1:I = 0x23

.field public static final FLOAD_2:I = 0x24

.field public static final FLOAD_3:I = 0x25

.field public static final FMT_BRANCH:I = 0x7

.field public static final FMT_CPI:I = 0x9

.field public static final FMT_INVALID:I = 0x0

.field public static final FMT_INVOKEINTERFACE:I = 0xd

.field public static final FMT_LDC:I = 0xe

.field public static final FMT_LITERAL_BYTE:I = 0xc

.field public static final FMT_LOCAL_1:I = 0xa

.field public static final FMT_LOCAL_2:I = 0xb

.field public static final FMT_LOOKUPSWITCH:I = 0x11

.field public static final FMT_MASK:I = 0x1f

.field public static final FMT_MULTIANEWARRAY:I = 0x12

.field public static final FMT_NO_ARGS:I = 0x1

.field public static final FMT_NO_ARGS_LOCALS_1:I = 0x2

.field public static final FMT_NO_ARGS_LOCALS_2:I = 0x3

.field public static final FMT_NO_ARGS_LOCALS_3:I = 0x4

.field public static final FMT_NO_ARGS_LOCALS_4:I = 0x5

.field public static final FMT_NO_ARGS_LOCALS_5:I = 0x6

.field public static final FMT_SIPUSH:I = 0xf

.field public static final FMT_TABLESWITCH:I = 0x10

.field public static final FMT_WIDE:I = 0x13

.field public static final FMT_WIDE_BRANCH:I = 0x8

.field public static final FMUL:I = 0x6a

.field public static final FNEG:I = 0x76

.field public static final FREM:I = 0x72

.field public static final FRETURN:I = 0xae

.field public static final FSTORE:I = 0x38

.field public static final FSTORE_0:I = 0x43

.field public static final FSTORE_1:I = 0x44

.field public static final FSTORE_2:I = 0x45

.field public static final FSTORE_3:I = 0x46

.field public static final FSUB:I = 0x66

.field public static final GETFIELD:I = 0xb4

.field public static final GETSTATIC:I = 0xb2

.field public static final GOTO:I = 0xa7

.field public static final GOTO_W:I = 0xc8

.field public static final I2B:I = 0x91

.field public static final I2C:I = 0x92

.field public static final I2D:I = 0x87

.field public static final I2F:I = 0x86

.field public static final I2L:I = 0x85

.field public static final I2S:I = 0x93

.field public static final IADD:I = 0x60

.field public static final IALOAD:I = 0x2e

.field public static final IAND:I = 0x7e

.field public static final IASTORE:I = 0x4f

.field public static final ICONST_0:I = 0x3

.field public static final ICONST_1:I = 0x4

.field public static final ICONST_2:I = 0x5

.field public static final ICONST_3:I = 0x6

.field public static final ICONST_4:I = 0x7

.field public static final ICONST_5:I = 0x8

.field public static final ICONST_M1:I = 0x2

.field public static final IDIV:I = 0x6c

.field public static final IFEQ:I = 0x99

.field public static final IFGE:I = 0x9c

.field public static final IFGT:I = 0x9d

.field public static final IFLE:I = 0x9e

.field public static final IFLT:I = 0x9b

.field public static final IFNE:I = 0x9a

.field public static final IFNONNULL:I = 0xc7

.field public static final IFNULL:I = 0xc6

.field public static final IF_ACMPEQ:I = 0xa5

.field public static final IF_ACMPNE:I = 0xa6

.field public static final IF_ICMPEQ:I = 0x9f

.field public static final IF_ICMPGE:I = 0xa2

.field public static final IF_ICMPGT:I = 0xa3

.field public static final IF_ICMPLE:I = 0xa4

.field public static final IF_ICMPLT:I = 0xa1

.field public static final IF_ICMPNE:I = 0xa0

.field public static final IINC:I = 0x84

.field public static final ILOAD:I = 0x15

.field public static final ILOAD_0:I = 0x1a

.field public static final ILOAD_1:I = 0x1b

.field public static final ILOAD_2:I = 0x1c

.field public static final ILOAD_3:I = 0x1d

.field public static final IMUL:I = 0x68

.field public static final INEG:I = 0x74

.field public static final INSTANCEOF:I = 0xc1

.field public static final INVOKEDYNAMIC:I = 0xba

.field public static final INVOKEINTERFACE:I = 0xb9

.field public static final INVOKESPECIAL:I = 0xb7

.field public static final INVOKESTATIC:I = 0xb8

.field public static final INVOKEVIRTUAL:I = 0xb6

.field public static final IOR:I = 0x80

.field public static final IREM:I = 0x70

.field public static final IRETURN:I = 0xac

.field public static final ISHL:I = 0x78

.field public static final ISHR:I = 0x7a

.field public static final ISTORE:I = 0x36

.field public static final ISTORE_0:I = 0x3b

.field public static final ISTORE_1:I = 0x3c

.field public static final ISTORE_2:I = 0x3d

.field public static final ISTORE_3:I = 0x3e

.field public static final ISUB:I = 0x64

.field public static final IUSHR:I = 0x7c

.field public static final IXOR:I = 0x82

.field public static final JSR:I = 0xa8

.field public static final JSR_W:I = 0xc9

.field public static final L2D:I = 0x8a

.field public static final L2F:I = 0x89

.field public static final L2I:I = 0x88

.field public static final LADD:I = 0x61

.field public static final LALOAD:I = 0x2f

.field public static final LAND:I = 0x7f

.field public static final LASTORE:I = 0x50

.field public static final LCMP:I = 0x94

.field public static final LCONST_0:I = 0x9

.field public static final LCONST_1:I = 0xa

.field public static final LDC:I = 0x12

.field public static final LDC2_W:I = 0x14

.field public static final LDC_W:I = 0x13

.field public static final LDIV:I = 0x6d

.field public static final LLOAD:I = 0x16

.field public static final LLOAD_0:I = 0x1e

.field public static final LLOAD_1:I = 0x1f

.field public static final LLOAD_2:I = 0x20

.field public static final LLOAD_3:I = 0x21

.field public static final LMUL:I = 0x69

.field public static final LNEG:I = 0x75

.field public static final LOOKUPSWITCH:I = 0xab

.field public static final LOR:I = 0x81

.field public static final LREM:I = 0x71

.field public static final LRETURN:I = 0xad

.field public static final LSHL:I = 0x79

.field public static final LSHR:I = 0x7b

.field public static final LSTORE:I = 0x37

.field public static final LSTORE_0:I = 0x3f

.field public static final LSTORE_1:I = 0x40

.field public static final LSTORE_2:I = 0x41

.field public static final LSTORE_3:I = 0x42

.field public static final LSUB:I = 0x65

.field public static final LUSHR:I = 0x7d

.field public static final LXOR:I = 0x83

.field public static final MONITORENTER:I = 0xc2

.field public static final MONITOREXIT:I = 0xc3

.field public static final MULTIANEWARRAY:I = 0xc5

.field public static final NEW:I = 0xbb

.field public static final NEWARRAY:I = 0xbc

.field public static final NEWARRAY_BOOLEAN:I = 0x4

.field public static final NEWARRAY_BYTE:I = 0x8

.field public static final NEWARRAY_CHAR:I = 0x5

.field public static final NEWARRAY_DOUBLE:I = 0x7

.field public static final NEWARRAY_FLOAT:I = 0x6

.field public static final NEWARRAY_INT:I = 0xa

.field public static final NEWARRAY_LONG:I = 0xb

.field public static final NEWARRAY_SHORT:I = 0x9

.field public static final NOP:I = 0x0

.field private static final OPCODE_DETAILS:Ljava/lang/String; = "00 - nop;01 - aconst_null;02 - iconst_m1;03 - iconst_0;04 - iconst_1;05 - iconst_2;06 - iconst_3;07 - iconst_4;08 - iconst_5;09 - lconst_0;0a - lconst_1;0b - fconst_0;0c - fconst_1;0d - fconst_2;0e - dconst_0;0f - dconst_1;10 y bipush;11 S sipush;12 L:IFcs ldc;13 p:IFcs ldc_w;14 p:DJ ldc2_w;15 l iload;16 m lload;17 l fload;18 m dload;19 l aload;1a 0 iload_0;1b 1 iload_1;1c 2 iload_2;1d 3 iload_3;1e 1 lload_0;1f 2 lload_1;20 3 lload_2;21 4 lload_3;22 0 fload_0;23 1 fload_1;24 2 fload_2;25 3 fload_3;26 1 dload_0;27 2 dload_1;28 3 dload_2;29 4 dload_3;2a 0 aload_0;2b 1 aload_1;2c 2 aload_2;2d 3 aload_3;2e - iaload;2f - laload;30 - faload;31 - daload;32 - aaload;33 - baload;34 - caload;35 - saload;36 - istore;37 - lstore;38 - fstore;39 - dstore;3a - astore;3b 0 istore_0;3c 1 istore_1;3d 2 istore_2;3e 3 istore_3;3f 1 lstore_0;40 2 lstore_1;41 3 lstore_2;42 4 lstore_3;43 0 fstore_0;44 1 fstore_1;45 2 fstore_2;46 3 fstore_3;47 1 dstore_0;48 2 dstore_1;49 3 dstore_2;4a 4 dstore_3;4b 0 astore_0;4c 1 astore_1;4d 2 astore_2;4e 3 astore_3;4f - iastore;50 - lastore;51 - fastore;52 - dastore;53 - aastore;54 - bastore;55 - castore;56 - sastore;57 - pop;58 - pop2;59 - dup;5a - dup_x1;5b - dup_x2;5c - dup2;5d - dup2_x1;5e - dup2_x2;5f - swap;60 - iadd;61 - ladd;62 - fadd;63 - dadd;64 - isub;65 - lsub;66 - fsub;67 - dsub;68 - imul;69 - lmul;6a - fmul;6b - dmul;6c - idiv;6d - ldiv;6e - fdiv;6f - ddiv;70 - irem;71 - lrem;72 - frem;73 - drem;74 - ineg;75 - lneg;76 - fneg;77 - dneg;78 - ishl;79 - lshl;7a - ishr;7b - lshr;7c - iushr;7d - lushr;7e - iand;7f - land;80 - ior;81 - lor;82 - ixor;83 - lxor;84 l iinc;85 - i2l;86 - i2f;87 - i2d;88 - l2i;89 - l2f;8a - l2d;8b - f2i;8c - f2l;8d - f2d;8e - d2i;8f - d2l;90 - d2f;91 - i2b;92 - i2c;93 - i2s;94 - lcmp;95 - fcmpl;96 - fcmpg;97 - dcmpl;98 - dcmpg;99 b ifeq;9a b ifne;9b b iflt;9c b ifge;9d b ifgt;9e b ifle;9f b if_icmpeq;a0 b if_icmpne;a1 b if_icmplt;a2 b if_icmpge;a3 b if_icmpgt;a4 b if_icmple;a5 b if_acmpeq;a6 b if_acmpne;a7 b goto;a8 b jsr;a9 l ret;aa T tableswitch;ab U lookupswitch;ac - ireturn;ad - lreturn;ae - freturn;af - dreturn;b0 - areturn;b1 - return;b2 p:f getstatic;b3 p:f putstatic;b4 p:f getfield;b5 p:f putfield;b6 p:m invokevirtual;b7 p:m invokespecial;b8 p:m invokestatic;b9 I:i invokeinterface;bb p:c new;bc y newarray;bd p:c anewarray;be - arraylength;bf - athrow;c0 p:c checkcast;c1 p:c instanceof;c2 - monitorenter;c3 - monitorexit;c4 W wide;c5 M:c multianewarray;c6 b ifnull;c7 b ifnonnull;c8 c goto_w;c9 c jsr_w;"

.field private static final OPCODE_INFO:[I

.field private static final OPCODE_NAMES:[Ljava/lang/String;

.field public static final POP:I = 0x57

.field public static final POP2:I = 0x58

.field public static final PUTFIELD:I = 0xb5

.field public static final PUTSTATIC:I = 0xb3

.field public static final RET:I = 0xa9

.field public static final RETURN:I = 0xb1

.field public static final SALOAD:I = 0x35

.field public static final SASTORE:I = 0x56

.field public static final SIPUSH:I = 0x11

.field public static final SWAP:I = 0x5f

.field public static final TABLESWITCH:I = 0xaa

.field public static final WIDE:I = 0xc4


# direct methods
.method static final constructor <clinit>()V
    .registers 8

    const/16 v3, 0x100

    const/4 v1, 0x0

    const/16 v2, 0x10

    new-array v0, v3, [I

    sput-object v0, Lcom/s1243808733/android/dx/cf/code/ByteOps;->OPCODE_INFO:[I

    new-array v0, v3, [Ljava/lang/String;

    sput-object v0, Lcom/s1243808733/android/dx/cf/code/ByteOps;->OPCODE_NAMES:[Ljava/lang/String;

    .line 559
    const-string v0, "00 - nop;01 - aconst_null;02 - iconst_m1;03 - iconst_0;04 - iconst_1;05 - iconst_2;06 - iconst_3;07 - iconst_4;08 - iconst_5;09 - lconst_0;0a - lconst_1;0b - fconst_0;0c - fconst_1;0d - fconst_2;0e - dconst_0;0f - dconst_1;10 y bipush;11 S sipush;12 L:IFcs ldc;13 p:IFcs ldc_w;14 p:DJ ldc2_w;15 l iload;16 m lload;17 l fload;18 m dload;19 l aload;1a 0 iload_0;1b 1 iload_1;1c 2 iload_2;1d 3 iload_3;1e 1 lload_0;1f 2 lload_1;20 3 lload_2;21 4 lload_3;22 0 fload_0;23 1 fload_1;24 2 fload_2;25 3 fload_3;26 1 dload_0;27 2 dload_1;28 3 dload_2;29 4 dload_3;2a 0 aload_0;2b 1 aload_1;2c 2 aload_2;2d 3 aload_3;2e - iaload;2f - laload;30 - faload;31 - daload;32 - aaload;33 - baload;34 - caload;35 - saload;36 - istore;37 - lstore;38 - fstore;39 - dstore;3a - astore;3b 0 istore_0;3c 1 istore_1;3d 2 istore_2;3e 3 istore_3;3f 1 lstore_0;40 2 lstore_1;41 3 lstore_2;42 4 lstore_3;43 0 fstore_0;44 1 fstore_1;45 2 fstore_2;46 3 fstore_3;47 1 dstore_0;48 2 dstore_1;49 3 dstore_2;4a 4 dstore_3;4b 0 astore_0;4c 1 astore_1;4d 2 astore_2;4e 3 astore_3;4f - iastore;50 - lastore;51 - fastore;52 - dastore;53 - aastore;54 - bastore;55 - castore;56 - sastore;57 - pop;58 - pop2;59 - dup;5a - dup_x1;5b - dup_x2;5c - dup2;5d - dup2_x1;5e - dup2_x2;5f - swap;60 - iadd;61 - ladd;62 - fadd;63 - dadd;64 - isub;65 - lsub;66 - fsub;67 - dsub;68 - imul;69 - lmul;6a - fmul;6b - dmul;6c - idiv;6d - ldiv;6e - fdiv;6f - ddiv;70 - irem;71 - lrem;72 - frem;73 - drem;74 - ineg;75 - lneg;76 - fneg;77 - dneg;78 - ishl;79 - lshl;7a - ishr;7b - lshr;7c - iushr;7d - lushr;7e - iand;7f - land;80 - ior;81 - lor;82 - ixor;83 - lxor;84 l iinc;85 - i2l;86 - i2f;87 - i2d;88 - l2i;89 - l2f;8a - l2d;8b - f2i;8c - f2l;8d - f2d;8e - d2i;8f - d2l;90 - d2f;91 - i2b;92 - i2c;93 - i2s;94 - lcmp;95 - fcmpl;96 - fcmpg;97 - dcmpl;98 - dcmpg;99 b ifeq;9a b ifne;9b b iflt;9c b ifge;9d b ifgt;9e b ifle;9f b if_icmpeq;a0 b if_icmpne;a1 b if_icmplt;a2 b if_icmpge;a3 b if_icmpgt;a4 b if_icmple;a5 b if_acmpeq;a6 b if_acmpne;a7 b goto;a8 b jsr;a9 l ret;aa T tableswitch;ab U lookupswitch;ac - ireturn;ad - lreturn;ae - freturn;af - dreturn;b0 - areturn;b1 - return;b2 p:f getstatic;b3 p:f putstatic;b4 p:f getfield;b5 p:f putfield;b6 p:m invokevirtual;b7 p:m invokespecial;b8 p:m invokestatic;b9 I:i invokeinterface;bb p:c new;bc y newarray;bd p:c anewarray;be - arraylength;bf - athrow;c0 p:c checkcast;c1 p:c instanceof;c2 - monitorenter;c3 - monitorexit;c4 W wide;c5 M:c multianewarray;c6 b ifnull;c7 b ifnonnull;c8 c goto_w;c9 c jsr_w;"

    invoke-virtual {v0}, Ljava/lang/String;->length()I

    move-result v5

    move v3, v1

    .line 613
    :goto_0
    if-lt v3, v5, :cond_0

    return-void

    .line 563
    :cond_0
    const-string v0, "00 - nop;01 - aconst_null;02 - iconst_m1;03 - iconst_0;04 - iconst_1;05 - iconst_2;06 - iconst_3;07 - iconst_4;08 - iconst_5;09 - lconst_0;0a - lconst_1;0b - fconst_0;0c - fconst_1;0d - fconst_2;0e - dconst_0;0f - dconst_1;10 y bipush;11 S sipush;12 L:IFcs ldc;13 p:IFcs ldc_w;14 p:DJ ldc2_w;15 l iload;16 m lload;17 l fload;18 m dload;19 l aload;1a 0 iload_0;1b 1 iload_1;1c 2 iload_2;1d 3 iload_3;1e 1 lload_0;1f 2 lload_1;20 3 lload_2;21 4 lload_3;22 0 fload_0;23 1 fload_1;24 2 fload_2;25 3 fload_3;26 1 dload_0;27 2 dload_1;28 3 dload_2;29 4 dload_3;2a 0 aload_0;2b 1 aload_1;2c 2 aload_2;2d 3 aload_3;2e - iaload;2f - laload;30 - faload;31 - daload;32 - aaload;33 - baload;34 - caload;35 - saload;36 - istore;37 - lstore;38 - fstore;39 - dstore;3a - astore;3b 0 istore_0;3c 1 istore_1;3d 2 istore_2;3e 3 istore_3;3f 1 lstore_0;40 2 lstore_1;41 3 lstore_2;42 4 lstore_3;43 0 fstore_0;44 1 fstore_1;45 2 fstore_2;46 3 fstore_3;47 1 dstore_0;48 2 dstore_1;49 3 dstore_2;4a 4 dstore_3;4b 0 astore_0;4c 1 astore_1;4d 2 astore_2;4e 3 astore_3;4f - iastore;50 - lastore;51 - fastore;52 - dastore;53 - aastore;54 - bastore;55 - castore;56 - sastore;57 - pop;58 - pop2;59 - dup;5a - dup_x1;5b - dup_x2;5c - dup2;5d - dup2_x1;5e - dup2_x2;5f - swap;60 - iadd;61 - ladd;62 - fadd;63 - dadd;64 - isub;65 - lsub;66 - fsub;67 - dsub;68 - imul;69 - lmul;6a - fmul;6b - dmul;6c - idiv;6d - ldiv;6e - fdiv;6f - ddiv;70 - irem;71 - lrem;72 - frem;73 - drem;74 - ineg;75 - lneg;76 - fneg;77 - dneg;78 - ishl;79 - lshl;7a - ishr;7b - lshr;7c - iushr;7d - lushr;7e - iand;7f - land;80 - ior;81 - lor;82 - ixor;83 - lxor;84 l iinc;85 - i2l;86 - i2f;87 - i2d;88 - l2i;89 - l2f;8a - l2d;8b - f2i;8c - f2l;8d - f2d;8e - d2i;8f - d2l;90 - d2f;91 - i2b;92 - i2c;93 - i2s;94 - lcmp;95 - fcmpl;96 - fcmpg;97 - dcmpl;98 - dcmpg;99 b ifeq;9a b ifne;9b b iflt;9c b ifge;9d b ifgt;9e b ifle;9f b if_icmpeq;a0 b if_icmpne;a1 b if_icmplt;a2 b if_icmpge;a3 b if_icmpgt;a4 b if_icmple;a5 b if_acmpeq;a6 b if_acmpne;a7 b goto;a8 b jsr;a9 l ret;aa T tableswitch;ab U lookupswitch;ac - ireturn;ad - lreturn;ae - freturn;af - dreturn;b0 - areturn;b1 - return;b2 p:f getstatic;b3 p:f putstatic;b4 p:f getfield;b5 p:f putfield;b6 p:m invokevirtual;b7 p:m invokespecial;b8 p:m invokestatic;b9 I:i invokeinterface;bb p:c new;bc y newarray;bd p:c anewarray;be - arraylength;bf - athrow;c0 p:c checkcast;c1 p:c instanceof;c2 - monitorenter;c3 - monitorexit;c4 W wide;c5 M:c multianewarray;c6 b ifnull;c7 b ifnonnull;c8 c goto_w;c9 c jsr_w;"

    invoke-virtual {v0, v3}, Ljava/lang/String;->charAt(I)C

    move-result v0

    invoke-static {v0, v2}, Ljava/lang/Character;->digit(CI)I

    move-result v0

    const-string v4, "00 - nop;01 - aconst_null;02 - iconst_m1;03 - iconst_0;04 - iconst_1;05 - iconst_2;06 - iconst_3;07 - iconst_4;08 - iconst_5;09 - lconst_0;0a - lconst_1;0b - fconst_0;0c - fconst_1;0d - fconst_2;0e - dconst_0;0f - dconst_1;10 y bipush;11 S sipush;12 L:IFcs ldc;13 p:IFcs ldc_w;14 p:DJ ldc2_w;15 l iload;16 m lload;17 l fload;18 m dload;19 l aload;1a 0 iload_0;1b 1 iload_1;1c 2 iload_2;1d 3 iload_3;1e 1 lload_0;1f 2 lload_1;20 3 lload_2;21 4 lload_3;22 0 fload_0;23 1 fload_1;24 2 fload_2;25 3 fload_3;26 1 dload_0;27 2 dload_1;28 3 dload_2;29 4 dload_3;2a 0 aload_0;2b 1 aload_1;2c 2 aload_2;2d 3 aload_3;2e - iaload;2f - laload;30 - faload;31 - daload;32 - aaload;33 - baload;34 - caload;35 - saload;36 - istore;37 - lstore;38 - fstore;39 - dstore;3a - astore;3b 0 istore_0;3c 1 istore_1;3d 2 istore_2;3e 3 istore_3;3f 1 lstore_0;40 2 lstore_1;41 3 lstore_2;42 4 lstore_3;43 0 fstore_0;44 1 fstore_1;45 2 fstore_2;46 3 fstore_3;47 1 dstore_0;48 2 dstore_1;49 3 dstore_2;4a 4 dstore_3;4b 0 astore_0;4c 1 astore_1;4d 2 astore_2;4e 3 astore_3;4f - iastore;50 - lastore;51 - fastore;52 - dastore;53 - aastore;54 - bastore;55 - castore;56 - sastore;57 - pop;58 - pop2;59 - dup;5a - dup_x1;5b - dup_x2;5c - dup2;5d - dup2_x1;5e - dup2_x2;5f - swap;60 - iadd;61 - ladd;62 - fadd;63 - dadd;64 - isub;65 - lsub;66 - fsub;67 - dsub;68 - imul;69 - lmul;6a - fmul;6b - dmul;6c - idiv;6d - ldiv;6e - fdiv;6f - ddiv;70 - irem;71 - lrem;72 - frem;73 - drem;74 - ineg;75 - lneg;76 - fneg;77 - dneg;78 - ishl;79 - lshl;7a - ishr;7b - lshr;7c - iushr;7d - lushr;7e - iand;7f - land;80 - ior;81 - lor;82 - ixor;83 - lxor;84 l iinc;85 - i2l;86 - i2f;87 - i2d;88 - l2i;89 - l2f;8a - l2d;8b - f2i;8c - f2l;8d - f2d;8e - d2i;8f - d2l;90 - d2f;91 - i2b;92 - i2c;93 - i2s;94 - lcmp;95 - fcmpl;96 - fcmpg;97 - dcmpl;98 - dcmpg;99 b ifeq;9a b ifne;9b b iflt;9c b ifge;9d b ifgt;9e b ifle;9f b if_icmpeq;a0 b if_icmpne;a1 b if_icmplt;a2 b if_icmpge;a3 b if_icmpgt;a4 b if_icmple;a5 b if_acmpeq;a6 b if_acmpne;a7 b goto;a8 b jsr;a9 l ret;aa T tableswitch;ab U lookupswitch;ac - ireturn;ad - lreturn;ae - freturn;af - dreturn;b0 - areturn;b1 - return;b2 p:f getstatic;b3 p:f putstatic;b4 p:f getfield;b5 p:f putfield;b6 p:m invokevirtual;b7 p:m invokespecial;b8 p:m invokestatic;b9 I:i invokeinterface;bb p:c new;bc y newarray;bd p:c anewarray;be - arraylength;bf - athrow;c0 p:c checkcast;c1 p:c instanceof;c2 - monitorenter;c3 - monitorexit;c4 W wide;c5 M:c multianewarray;c6 b ifnull;c7 b ifnonnull;c8 c goto_w;c9 c jsr_w;"

    add-int/lit8 v6, v3, 0x1

    invoke-virtual {v4, v6}, Ljava/lang/String;->charAt(I)C

    move-result v4

    invoke-static {v4, v2}, Ljava/lang/Character;->digit(CI)I

    move-result v4

    shl-int/lit8 v0, v0, 0x4

    or-int v6, v4, v0

    .line 565
    const-string v0, "00 - nop;01 - aconst_null;02 - iconst_m1;03 - iconst_0;04 - iconst_1;05 - iconst_2;06 - iconst_3;07 - iconst_4;08 - iconst_5;09 - lconst_0;0a - lconst_1;0b - fconst_0;0c - fconst_1;0d - fconst_2;0e - dconst_0;0f - dconst_1;10 y bipush;11 S sipush;12 L:IFcs ldc;13 p:IFcs ldc_w;14 p:DJ ldc2_w;15 l iload;16 m lload;17 l fload;18 m dload;19 l aload;1a 0 iload_0;1b 1 iload_1;1c 2 iload_2;1d 3 iload_3;1e 1 lload_0;1f 2 lload_1;20 3 lload_2;21 4 lload_3;22 0 fload_0;23 1 fload_1;24 2 fload_2;25 3 fload_3;26 1 dload_0;27 2 dload_1;28 3 dload_2;29 4 dload_3;2a 0 aload_0;2b 1 aload_1;2c 2 aload_2;2d 3 aload_3;2e - iaload;2f - laload;30 - faload;31 - daload;32 - aaload;33 - baload;34 - caload;35 - saload;36 - istore;37 - lstore;38 - fstore;39 - dstore;3a - astore;3b 0 istore_0;3c 1 istore_1;3d 2 istore_2;3e 3 istore_3;3f 1 lstore_0;40 2 lstore_1;41 3 lstore_2;42 4 lstore_3;43 0 fstore_0;44 1 fstore_1;45 2 fstore_2;46 3 fstore_3;47 1 dstore_0;48 2 dstore_1;49 3 dstore_2;4a 4 dstore_3;4b 0 astore_0;4c 1 astore_1;4d 2 astore_2;4e 3 astore_3;4f - iastore;50 - lastore;51 - fastore;52 - dastore;53 - aastore;54 - bastore;55 - castore;56 - sastore;57 - pop;58 - pop2;59 - dup;5a - dup_x1;5b - dup_x2;5c - dup2;5d - dup2_x1;5e - dup2_x2;5f - swap;60 - iadd;61 - ladd;62 - fadd;63 - dadd;64 - isub;65 - lsub;66 - fsub;67 - dsub;68 - imul;69 - lmul;6a - fmul;6b - dmul;6c - idiv;6d - ldiv;6e - fdiv;6f - ddiv;70 - irem;71 - lrem;72 - frem;73 - drem;74 - ineg;75 - lneg;76 - fneg;77 - dneg;78 - ishl;79 - lshl;7a - ishr;7b - lshr;7c - iushr;7d - lushr;7e - iand;7f - land;80 - ior;81 - lor;82 - ixor;83 - lxor;84 l iinc;85 - i2l;86 - i2f;87 - i2d;88 - l2i;89 - l2f;8a - l2d;8b - f2i;8c - f2l;8d - f2d;8e - d2i;8f - d2l;90 - d2f;91 - i2b;92 - i2c;93 - i2s;94 - lcmp;95 - fcmpl;96 - fcmpg;97 - dcmpl;98 - dcmpg;99 b ifeq;9a b ifne;9b b iflt;9c b ifge;9d b ifgt;9e b ifle;9f b if_icmpeq;a0 b if_icmpne;a1 b if_icmplt;a2 b if_icmpge;a3 b if_icmpgt;a4 b if_icmple;a5 b if_acmpeq;a6 b if_acmpne;a7 b goto;a8 b jsr;a9 l ret;aa T tableswitch;ab U lookupswitch;ac - ireturn;ad - lreturn;ae - freturn;af - dreturn;b0 - areturn;b1 - return;b2 p:f getstatic;b3 p:f putstatic;b4 p:f getfield;b5 p:f putfield;b6 p:m invokevirtual;b7 p:m invokespecial;b8 p:m invokestatic;b9 I:i invokeinterface;bb p:c new;bc y newarray;bd p:c anewarray;be - arraylength;bf - athrow;c0 p:c checkcast;c1 p:c instanceof;c2 - monitorenter;c3 - monitorexit;c4 W wide;c5 M:c multianewarray;c6 b ifnull;c7 b ifnonnull;c8 c goto_w;c9 c jsr_w;"

    add-int/lit8 v4, v3, 0x3

    invoke-virtual {v0, v4}, Ljava/lang/String;->charAt(I)C

    move-result v0

    sparse-switch v0, :sswitch_data_0

    move v0, v1

    .line 589
    :goto_1
    add-int/lit8 v3, v3, 0x5

    .line 590
    const-string v4, "00 - nop;01 - aconst_null;02 - iconst_m1;03 - iconst_0;04 - iconst_1;05 - iconst_2;06 - iconst_3;07 - iconst_4;08 - iconst_5;09 - lconst_0;0a - lconst_1;0b - fconst_0;0c - fconst_1;0d - fconst_2;0e - dconst_0;0f - dconst_1;10 y bipush;11 S sipush;12 L:IFcs ldc;13 p:IFcs ldc_w;14 p:DJ ldc2_w;15 l iload;16 m lload;17 l fload;18 m dload;19 l aload;1a 0 iload_0;1b 1 iload_1;1c 2 iload_2;1d 3 iload_3;1e 1 lload_0;1f 2 lload_1;20 3 lload_2;21 4 lload_3;22 0 fload_0;23 1 fload_1;24 2 fload_2;25 3 fload_3;26 1 dload_0;27 2 dload_1;28 3 dload_2;29 4 dload_3;2a 0 aload_0;2b 1 aload_1;2c 2 aload_2;2d 3 aload_3;2e - iaload;2f - laload;30 - faload;31 - daload;32 - aaload;33 - baload;34 - caload;35 - saload;36 - istore;37 - lstore;38 - fstore;39 - dstore;3a - astore;3b 0 istore_0;3c 1 istore_1;3d 2 istore_2;3e 3 istore_3;3f 1 lstore_0;40 2 lstore_1;41 3 lstore_2;42 4 lstore_3;43 0 fstore_0;44 1 fstore_1;45 2 fstore_2;46 3 fstore_3;47 1 dstore_0;48 2 dstore_1;49 3 dstore_2;4a 4 dstore_3;4b 0 astore_0;4c 1 astore_1;4d 2 astore_2;4e 3 astore_3;4f - iastore;50 - lastore;51 - fastore;52 - dastore;53 - aastore;54 - bastore;55 - castore;56 - sastore;57 - pop;58 - pop2;59 - dup;5a - dup_x1;5b - dup_x2;5c - dup2;5d - dup2_x1;5e - dup2_x2;5f - swap;60 - iadd;61 - ladd;62 - fadd;63 - dadd;64 - isub;65 - lsub;66 - fsub;67 - dsub;68 - imul;69 - lmul;6a - fmul;6b - dmul;6c - idiv;6d - ldiv;6e - fdiv;6f - ddiv;70 - irem;71 - lrem;72 - frem;73 - drem;74 - ineg;75 - lneg;76 - fneg;77 - dneg;78 - ishl;79 - lshl;7a - ishr;7b - lshr;7c - iushr;7d - lushr;7e - iand;7f - land;80 - ior;81 - lor;82 - ixor;83 - lxor;84 l iinc;85 - i2l;86 - i2f;87 - i2d;88 - l2i;89 - l2f;8a - l2d;8b - f2i;8c - f2l;8d - f2d;8e - d2i;8f - d2l;90 - d2f;91 - i2b;92 - i2c;93 - i2s;94 - lcmp;95 - fcmpl;96 - fcmpg;97 - dcmpl;98 - dcmpg;99 b ifeq;9a b ifne;9b b iflt;9c b ifge;9d b ifgt;9e b ifle;9f b if_icmpeq;a0 b if_icmpne;a1 b if_icmplt;a2 b if_icmpge;a3 b if_icmpgt;a4 b if_icmple;a5 b if_acmpeq;a6 b if_acmpne;a7 b goto;a8 b jsr;a9 l ret;aa T tableswitch;ab U lookupswitch;ac - ireturn;ad - lreturn;ae - freturn;af - dreturn;b0 - areturn;b1 - return;b2 p:f getstatic;b3 p:f putstatic;b4 p:f getfield;b5 p:f putfield;b6 p:m invokevirtual;b7 p:m invokespecial;b8 p:m invokestatic;b9 I:i invokeinterface;bb p:c new;bc y newarray;bd p:c anewarray;be - arraylength;bf - athrow;c0 p:c checkcast;c1 p:c instanceof;c2 - monitorenter;c3 - monitorexit;c4 W wide;c5 M:c multianewarray;c6 b ifnull;c7 b ifnonnull;c8 c goto_w;c9 c jsr_w;"

    add-int/lit8 v7, v3, -0x1

    invoke-virtual {v4, v7}, Ljava/lang/String;->charAt(I)C

    move-result v4

    const/16 v7, 0x3a

    if-ne v4, v7, :cond_1

    move v4, v0

    .line 593
    :goto_2
    const-string v0, "00 - nop;01 - aconst_null;02 - iconst_m1;03 - iconst_0;04 - iconst_1;05 - iconst_2;06 - iconst_3;07 - iconst_4;08 - iconst_5;09 - lconst_0;0a - lconst_1;0b - fconst_0;0c - fconst_1;0d - fconst_2;0e - dconst_0;0f - dconst_1;10 y bipush;11 S sipush;12 L:IFcs ldc;13 p:IFcs ldc_w;14 p:DJ ldc2_w;15 l iload;16 m lload;17 l fload;18 m dload;19 l aload;1a 0 iload_0;1b 1 iload_1;1c 2 iload_2;1d 3 iload_3;1e 1 lload_0;1f 2 lload_1;20 3 lload_2;21 4 lload_3;22 0 fload_0;23 1 fload_1;24 2 fload_2;25 3 fload_3;26 1 dload_0;27 2 dload_1;28 3 dload_2;29 4 dload_3;2a 0 aload_0;2b 1 aload_1;2c 2 aload_2;2d 3 aload_3;2e - iaload;2f - laload;30 - faload;31 - daload;32 - aaload;33 - baload;34 - caload;35 - saload;36 - istore;37 - lstore;38 - fstore;39 - dstore;3a - astore;3b 0 istore_0;3c 1 istore_1;3d 2 istore_2;3e 3 istore_3;3f 1 lstore_0;40 2 lstore_1;41 3 lstore_2;42 4 lstore_3;43 0 fstore_0;44 1 fstore_1;45 2 fstore_2;46 3 fstore_3;47 1 dstore_0;48 2 dstore_1;49 3 dstore_2;4a 4 dstore_3;4b 0 astore_0;4c 1 astore_1;4d 2 astore_2;4e 3 astore_3;4f - iastore;50 - lastore;51 - fastore;52 - dastore;53 - aastore;54 - bastore;55 - castore;56 - sastore;57 - pop;58 - pop2;59 - dup;5a - dup_x1;5b - dup_x2;5c - dup2;5d - dup2_x1;5e - dup2_x2;5f - swap;60 - iadd;61 - ladd;62 - fadd;63 - dadd;64 - isub;65 - lsub;66 - fsub;67 - dsub;68 - imul;69 - lmul;6a - fmul;6b - dmul;6c - idiv;6d - ldiv;6e - fdiv;6f - ddiv;70 - irem;71 - lrem;72 - frem;73 - drem;74 - ineg;75 - lneg;76 - fneg;77 - dneg;78 - ishl;79 - lshl;7a - ishr;7b - lshr;7c - iushr;7d - lushr;7e - iand;7f - land;80 - ior;81 - lor;82 - ixor;83 - lxor;84 l iinc;85 - i2l;86 - i2f;87 - i2d;88 - l2i;89 - l2f;8a - l2d;8b - f2i;8c - f2l;8d - f2d;8e - d2i;8f - d2l;90 - d2f;91 - i2b;92 - i2c;93 - i2s;94 - lcmp;95 - fcmpl;96 - fcmpg;97 - dcmpl;98 - dcmpg;99 b ifeq;9a b ifne;9b b iflt;9c b ifge;9d b ifgt;9e b ifle;9f b if_icmpeq;a0 b if_icmpne;a1 b if_icmplt;a2 b if_icmpge;a3 b if_icmpgt;a4 b if_icmple;a5 b if_acmpeq;a6 b if_acmpne;a7 b goto;a8 b jsr;a9 l ret;aa T tableswitch;ab U lookupswitch;ac - ireturn;ad - lreturn;ae - freturn;af - dreturn;b0 - areturn;b1 - return;b2 p:f getstatic;b3 p:f putstatic;b4 p:f getfield;b5 p:f putfield;b6 p:m invokevirtual;b7 p:m invokespecial;b8 p:m invokestatic;b9 I:i invokeinterface;bb p:c new;bc y newarray;bd p:c anewarray;be - arraylength;bf - athrow;c0 p:c checkcast;c1 p:c instanceof;c2 - monitorenter;c3 - monitorexit;c4 W wide;c5 M:c multianewarray;c6 b ifnull;c7 b ifnonnull;c8 c goto_w;c9 c jsr_w;"

    invoke-virtual {v0, v3}, Ljava/lang/String;->charAt(I)C

    move-result v0

    sparse-switch v0, :sswitch_data_1

    .line 607
    add-int/lit8 v3, v3, 0x1

    .line 610
    :goto_3
    const-string v0, "00 - nop;01 - aconst_null;02 - iconst_m1;03 - iconst_0;04 - iconst_1;05 - iconst_2;06 - iconst_3;07 - iconst_4;08 - iconst_5;09 - lconst_0;0a - lconst_1;0b - fconst_0;0c - fconst_1;0d - fconst_2;0e - dconst_0;0f - dconst_1;10 y bipush;11 S sipush;12 L:IFcs ldc;13 p:IFcs ldc_w;14 p:DJ ldc2_w;15 l iload;16 m lload;17 l fload;18 m dload;19 l aload;1a 0 iload_0;1b 1 iload_1;1c 2 iload_2;1d 3 iload_3;1e 1 lload_0;1f 2 lload_1;20 3 lload_2;21 4 lload_3;22 0 fload_0;23 1 fload_1;24 2 fload_2;25 3 fload_3;26 1 dload_0;27 2 dload_1;28 3 dload_2;29 4 dload_3;2a 0 aload_0;2b 1 aload_1;2c 2 aload_2;2d 3 aload_3;2e - iaload;2f - laload;30 - faload;31 - daload;32 - aaload;33 - baload;34 - caload;35 - saload;36 - istore;37 - lstore;38 - fstore;39 - dstore;3a - astore;3b 0 istore_0;3c 1 istore_1;3d 2 istore_2;3e 3 istore_3;3f 1 lstore_0;40 2 lstore_1;41 3 lstore_2;42 4 lstore_3;43 0 fstore_0;44 1 fstore_1;45 2 fstore_2;46 3 fstore_3;47 1 dstore_0;48 2 dstore_1;49 3 dstore_2;4a 4 dstore_3;4b 0 astore_0;4c 1 astore_1;4d 2 astore_2;4e 3 astore_3;4f - iastore;50 - lastore;51 - fastore;52 - dastore;53 - aastore;54 - bastore;55 - castore;56 - sastore;57 - pop;58 - pop2;59 - dup;5a - dup_x1;5b - dup_x2;5c - dup2;5d - dup2_x1;5e - dup2_x2;5f - swap;60 - iadd;61 - ladd;62 - fadd;63 - dadd;64 - isub;65 - lsub;66 - fsub;67 - dsub;68 - imul;69 - lmul;6a - fmul;6b - dmul;6c - idiv;6d - ldiv;6e - fdiv;6f - ddiv;70 - irem;71 - lrem;72 - frem;73 - drem;74 - ineg;75 - lneg;76 - fneg;77 - dneg;78 - ishl;79 - lshl;7a - ishr;7b - lshr;7c - iushr;7d - lushr;7e - iand;7f - land;80 - ior;81 - lor;82 - ixor;83 - lxor;84 l iinc;85 - i2l;86 - i2f;87 - i2d;88 - l2i;89 - l2f;8a - l2d;8b - f2i;8c - f2l;8d - f2d;8e - d2i;8f - d2l;90 - d2f;91 - i2b;92 - i2c;93 - i2s;94 - lcmp;95 - fcmpl;96 - fcmpg;97 - dcmpl;98 - dcmpg;99 b ifeq;9a b ifne;9b b iflt;9c b ifge;9d b ifgt;9e b ifle;9f b if_icmpeq;a0 b if_icmpne;a1 b if_icmplt;a2 b if_icmpge;a3 b if_icmpgt;a4 b if_icmple;a5 b if_acmpeq;a6 b if_acmpne;a7 b goto;a8 b jsr;a9 l ret;aa T tableswitch;ab U lookupswitch;ac - ireturn;ad - lreturn;ae - freturn;af - dreturn;b0 - areturn;b1 - return;b2 p:f getstatic;b3 p:f putstatic;b4 p:f getfield;b5 p:f putfield;b6 p:m invokevirtual;b7 p:m invokespecial;b8 p:m invokestatic;b9 I:i invokeinterface;bb p:c new;bc y newarray;bd p:c anewarray;be - arraylength;bf - athrow;c0 p:c checkcast;c1 p:c instanceof;c2 - monitorenter;c3 - monitorexit;c4 W wide;c5 M:c multianewarray;c6 b ifnull;c7 b ifnonnull;c8 c goto_w;c9 c jsr_w;"

    const/16 v7, 0x3b

    invoke-virtual {v0, v7, v3}, Ljava/lang/String;->indexOf(II)I

    move-result v0

    .line 611
    sget-object v7, Lcom/s1243808733/android/dx/cf/code/ByteOps;->OPCODE_INFO:[I

    aput v4, v7, v6

    .line 612
    sget-object v4, Lcom/s1243808733/android/dx/cf/code/ByteOps;->OPCODE_NAMES:[Ljava/lang/String;

    const-string v7, "00 - nop;01 - aconst_null;02 - iconst_m1;03 - iconst_0;04 - iconst_1;05 - iconst_2;06 - iconst_3;07 - iconst_4;08 - iconst_5;09 - lconst_0;0a - lconst_1;0b - fconst_0;0c - fconst_1;0d - fconst_2;0e - dconst_0;0f - dconst_1;10 y bipush;11 S sipush;12 L:IFcs ldc;13 p:IFcs ldc_w;14 p:DJ ldc2_w;15 l iload;16 m lload;17 l fload;18 m dload;19 l aload;1a 0 iload_0;1b 1 iload_1;1c 2 iload_2;1d 3 iload_3;1e 1 lload_0;1f 2 lload_1;20 3 lload_2;21 4 lload_3;22 0 fload_0;23 1 fload_1;24 2 fload_2;25 3 fload_3;26 1 dload_0;27 2 dload_1;28 3 dload_2;29 4 dload_3;2a 0 aload_0;2b 1 aload_1;2c 2 aload_2;2d 3 aload_3;2e - iaload;2f - laload;30 - faload;31 - daload;32 - aaload;33 - baload;34 - caload;35 - saload;36 - istore;37 - lstore;38 - fstore;39 - dstore;3a - astore;3b 0 istore_0;3c 1 istore_1;3d 2 istore_2;3e 3 istore_3;3f 1 lstore_0;40 2 lstore_1;41 3 lstore_2;42 4 lstore_3;43 0 fstore_0;44 1 fstore_1;45 2 fstore_2;46 3 fstore_3;47 1 dstore_0;48 2 dstore_1;49 3 dstore_2;4a 4 dstore_3;4b 0 astore_0;4c 1 astore_1;4d 2 astore_2;4e 3 astore_3;4f - iastore;50 - lastore;51 - fastore;52 - dastore;53 - aastore;54 - bastore;55 - castore;56 - sastore;57 - pop;58 - pop2;59 - dup;5a - dup_x1;5b - dup_x2;5c - dup2;5d - dup2_x1;5e - dup2_x2;5f - swap;60 - iadd;61 - ladd;62 - fadd;63 - dadd;64 - isub;65 - lsub;66 - fsub;67 - dsub;68 - imul;69 - lmul;6a - fmul;6b - dmul;6c - idiv;6d - ldiv;6e - fdiv;6f - ddiv;70 - irem;71 - lrem;72 - frem;73 - drem;74 - ineg;75 - lneg;76 - fneg;77 - dneg;78 - ishl;79 - lshl;7a - ishr;7b - lshr;7c - iushr;7d - lushr;7e - iand;7f - land;80 - ior;81 - lor;82 - ixor;83 - lxor;84 l iinc;85 - i2l;86 - i2f;87 - i2d;88 - l2i;89 - l2f;8a - l2d;8b - f2i;8c - f2l;8d - f2d;8e - d2i;8f - d2l;90 - d2f;91 - i2b;92 - i2c;93 - i2s;94 - lcmp;95 - fcmpl;96 - fcmpg;97 - dcmpl;98 - dcmpg;99 b ifeq;9a b ifne;9b b iflt;9c b ifge;9d b ifgt;9e b ifle;9f b if_icmpeq;a0 b if_icmpne;a1 b if_icmplt;a2 b if_icmpge;a3 b if_icmpgt;a4 b if_icmple;a5 b if_acmpeq;a6 b if_acmpne;a7 b goto;a8 b jsr;a9 l ret;aa T tableswitch;ab U lookupswitch;ac - ireturn;ad - lreturn;ae - freturn;af - dreturn;b0 - areturn;b1 - return;b2 p:f getstatic;b3 p:f putstatic;b4 p:f getfield;b5 p:f putfield;b6 p:m invokevirtual;b7 p:m invokespecial;b8 p:m invokestatic;b9 I:i invokeinterface;bb p:c new;bc y newarray;bd p:c anewarray;be - arraylength;bf - athrow;c0 p:c checkcast;c1 p:c instanceof;c2 - monitorenter;c3 - monitorexit;c4 W wide;c5 M:c multianewarray;c6 b ifnull;c7 b ifnonnull;c8 c goto_w;c9 c jsr_w;"

    invoke-virtual {v7, v3, v0}, Ljava/lang/String;->substring(II)Ljava/lang/String;

    move-result-object v3

    aput-object v3, v4, v6

    .line 613
    add-int/lit8 v0, v0, 0x1

    move v3, v0

    goto :goto_0

    .line 567
    :sswitch_0
    const/4 v0, 0x1

    goto :goto_1

    .line 568
    :sswitch_1
    const/4 v0, 0x2

    goto :goto_1

    .line 569
    :sswitch_2
    const/4 v0, 0x3

    goto :goto_1

    .line 570
    :sswitch_3
    const/4 v0, 0x4

    goto :goto_1

    .line 571
    :sswitch_4
    const/4 v0, 0x5

    goto :goto_1

    .line 572
    :sswitch_5
    const/4 v0, 0x6

    goto :goto_1

    .line 573
    :sswitch_6
    const/4 v0, 0x7

    goto :goto_1

    .line 574
    :sswitch_7
    const/16 v0, 0x8

    goto :goto_1

    .line 575
    :sswitch_8
    const/16 v0, 0x9

    goto :goto_1

    .line 576
    :sswitch_9
    const/16 v0, 0xa

    goto :goto_1

    .line 577
    :sswitch_a
    const/16 v0, 0xb

    goto :goto_1

    .line 578
    :sswitch_b
    const/16 v0, 0xc

    goto :goto_1

    .line 579
    :sswitch_c
    const/16 v0, 0xd

    goto :goto_1

    .line 580
    :sswitch_d
    const/16 v0, 0xe

    goto :goto_1

    .line 581
    :sswitch_e
    const/16 v0, 0xf

    goto :goto_1

    :sswitch_f
    move v0, v2

    .line 582
    goto :goto_1

    .line 583
    :sswitch_10
    const/16 v0, 0x11

    goto :goto_1

    .line 584
    :sswitch_11
    const/16 v0, 0x12

    goto :goto_1

    .line 585
    :sswitch_12
    const/16 v0, 0x13

    goto :goto_1

    .line 594
    :sswitch_13
    or-int/lit8 v4, v4, 0x20

    .line 605
    :goto_4
    add-int/lit8 v0, v3, 0x1

    move v3, v0

    goto :goto_2

    .line 595
    :sswitch_14
    or-int/lit8 v4, v4, 0x40

    goto :goto_4

    .line 596
    :sswitch_15
    or-int/lit16 v4, v4, 0x80

    goto :goto_4

    .line 597
    :sswitch_16
    or-int/lit16 v4, v4, 0x100

    goto :goto_4

    .line 598
    :sswitch_17
    or-int/lit16 v4, v4, 0x200

    goto :goto_4

    .line 599
    :sswitch_18
    or-int/lit16 v4, v4, 0x400

    goto :goto_4

    .line 600
    :sswitch_19
    or-int/lit16 v4, v4, 0x800

    goto :goto_4

    .line 601
    :sswitch_1a
    or-int/lit16 v4, v4, 0x1000

    goto :goto_4

    .line 602
    :sswitch_1b
    or-int/lit16 v4, v4, 0x2000

    goto :goto_4

    :cond_1
    move v4, v0

    goto :goto_3

    .line 565
    :sswitch_data_0
    .sparse-switch
        0x2d -> :sswitch_0
        0x30 -> :sswitch_1
        0x31 -> :sswitch_2
        0x32 -> :sswitch_3
        0x33 -> :sswitch_4
        0x34 -> :sswitch_5
        0x49 -> :sswitch_c
        0x4c -> :sswitch_d
        0x4d -> :sswitch_11
        0x53 -> :sswitch_e
        0x54 -> :sswitch_f
        0x55 -> :sswitch_10
        0x57 -> :sswitch_12
        0x62 -> :sswitch_6
        0x63 -> :sswitch_7
        0x6c -> :sswitch_9
        0x6d -> :sswitch_a
        0x70 -> :sswitch_8
        0x79 -> :sswitch_b
    .end sparse-switch

    .line 593
    :sswitch_data_1
    .sparse-switch
        0x44 -> :sswitch_16
        0x46 -> :sswitch_14
        0x49 -> :sswitch_13
        0x4a -> :sswitch_15
        0x63 -> :sswitch_17
        0x66 -> :sswitch_19
        0x69 -> :sswitch_1b
        0x6d -> :sswitch_1a
        0x73 -> :sswitch_18
    .end sparse-switch
.end method

.method constructor <init>()V
    .registers 1

    .line 620
    invoke-direct {p0}, Ljava/lang/Object;-><init>()V

    return-void
.end method

.method public static opInfo(I)I
    .registers 2

    .line 648
    sget-object v0, Lcom/s1243808733/android/dx/cf/code/ByteOps;->OPCODE_INFO:[I

    aget v0, v0, p0

    return v0
.end method

.method public static opName(I)Ljava/lang/String;
    .registers 3

    .line 631
    sget-object v0, Lcom/s1243808733/android/dx/cf/code/ByteOps;->OPCODE_NAMES:[Ljava/lang/String;

    aget-object v0, v0, p0

    .line 633
    if-nez v0, :cond_0

    .line 634
    new-instance v0, Ljava/lang/StringBuffer;

    invoke-direct {v0}, Ljava/lang/StringBuffer;-><init>()V

    const-string v1, "unused_"

    invoke-virtual {v0, v1}, Ljava/lang/StringBuffer;->append(Ljava/lang/String;)Ljava/lang/StringBuffer;

    move-result-object v0

    invoke-static {p0}, Lcom/s1243808733/android/dx/util/Hex;->u1(I)Ljava/lang/String;

    move-result-object v1

    invoke-virtual {v0, v1}, Ljava/lang/StringBuffer;->append(Ljava/lang/String;)Ljava/lang/StringBuffer;

    move-result-object v0

    invoke-virtual {v0}, Ljava/lang/StringBuffer;->toString()Ljava/lang/String;

    move-result-object v0

    .line 635
    sget-object v1, Lcom/s1243808733/android/dx/cf/code/ByteOps;->OPCODE_NAMES:[Ljava/lang/String;

    aput-object v0, v1, p0

    .line 638
    :cond_0
    return-object v0
.end method
